[
  {
    "sessionId": "d79c95e4-c17f-4186-8376-8f6ef3cd2806",
    "reason": "clear",
    "endedAt": "2026-03-26T04:55:40.212Z",
    "feature": null,
    "phase": null,
    "progress": null
  },
  {
    "sessionId": "848af447-2ced-4e1d-8f4c-c8cf87d61198",
    "reason": "prompt_input_exit",
    "endedAt": "2026-03-26T14:26:59.212Z",
    "feature": null,
    "phase": null,
    "progress": null
  },
  {
    "sessionId": "c67d861c-ad4c-4402-9121-04714e523a57",
    "reason": "prompt_input_exit",
    "endedAt": "2026-03-26T14:28:21.601Z",
    "feature": null,
    "phase": null,
    "progress": null
  },
  {
    "sessionId": "33d4b8ab-6cf5-4562-a71a-25656514a7cd",
    "reason": "logout",
    "endedAt": "2026-03-26T14:30:11.467Z",
    "feature": null,
    "phase": null,
    "progress": null
  },
  {
    "sessionId": "e7c828bb-d62b-4312-82c9-3a79795dc9e4",
    "reason": "clear",
    "endedAt": "2026-03-27T07:36:58.318Z",
    "feature": null,
    "phase": null,
    "progress": null
  },
  {
    "sessionId": "4b81dfe3-b884-47c5-929c-9f06bb604300",
    "reason": "clear",
    "endedAt": "2026-03-27T08:35:32.129Z",
    "feature": null,
    "phase": null,
    "progress": null
  },
  {
    "sessionId": "314f18cc-f498-44e9-afd8-468a62ec3ccf",
    "reason": "clear",
    "endedAt": "2026-03-27T11:38:57.526Z",
    "feature": null,
    "phase": null,
    "progress": null
  },
  {
    "sessionId": "7db6267b-9996-4804-9778-dd947ac4208d",
    "reason": "prompt_input_exit",
    "endedAt": "2026-03-27T13:18:25.755Z",
    "feature": null,
    "phase": null,
    "progress": null
  },
  {
    "sessionId": "3d431671-99d2-4e84-8750-1dd7f757c072",
    "reason": "prompt_input_exit",
    "endedAt": "2026-03-27T13:19:38.362Z",
    "feature": null,
    "phase": null,
    "progress": null
  },
  {
    "sessionId": "aff336fb-b989-4f88-a907-d1ab21b7c417",
    "reason": "clear",
    "endedAt": "2026-03-28T05:50:01.061Z",
    "feature": null,
    "phase": null,
    "progress": null
  },
  {
    "sessionId": "20fdfb48-7bf3-4220-b7cc-bf5ae407a1be",
    "reason": "clear",
    "endedAt": "2026-03-28T09:35:08.322Z",
    "feature": null,
    "phase": null,
    "progress": null
  },
  {
    "sessionId": "76606a97-da78-4375-a388-625009dd959b",
    "reason": "clear",
    "endedAt": "2026-03-28T13:06:23.143Z",
    "feature": null,
    "phase": null,
    "progress": null
  },
  {
    "sessionId": "0a0577b1-5529-4403-b4e3-4a5d7a520396",
    "reason": "clear",
    "endedAt": "2026-03-29T00:20:07.093Z",
    "feature": null,
    "phase": null,
    "progress": null
  },
  {
    "sessionId": "2b0eea05-a69a-45e8-bb6f-8717c5148a0c",
    "reason": "clear",
    "endedAt": "2026-03-29T09:48:14.391Z",
    "feature": null,
    "phase": null,
    "progress": null
  },
  {
    "sessionId": "563d26b1-e52d-499a-9cd8-843f024d165a",
    "reason": "clear",
    "endedAt": "2026-03-29T12:26:17.615Z",
    "feature": null,
    "phase": null,
    "progress": null
  },
  {
    "sessionId": "c932d23d-810d-48a1-b0e3-224e87a006bd",
    "reason": "clear",
    "endedAt": "2026-03-29T14:14:16.849Z",
    "feature": null,
    "phase": null,
    "progress": null
  }
]